fcsparser/__init__.py
fcsparser/api.py
fcsparser/tests/__init__.py
fcsparser/tests/data/FlowCytometers/Cytek_xP5/Cytek_xP5.fcs
fcsparser/tests/data/FlowCytometers/FACSCaliburHTS/Sample_Well_A02.fcs
fcsparser/tests/data/FlowCytometers/FACS_Diva/facs_diva_test.fcs
fcsparser/tests/data/FlowCytometers/Fortessa/FCS_3.0_Fortessa_PBS_Specimen_001_A1_A01.fcs
fcsparser/tests/data/FlowCytometers/GuavaMuse/Guava Muse.fcs
fcsparser/tests/data/FlowCytometers/HTS_BD_LSR-II/HTS_BD_LSR_II_Mixed_Specimen_001_D6_D06.fcs
fcsparser/tests/data/FlowCytometers/MiltenyiBiotec/FCS2.0/EY_2013-07-19_PBS_FCS_2.0_Custom_Without_Add_Well_A1.001.fcs
fcsparser/tests/data/FlowCytometers/MiltenyiBiotec/FCS3.0/FCS3.0_Custom_Compatible.fcs
fcsparser/tests/data/FlowCytometers/MiltenyiBiotec/FCS3.1/EY_2013-07-19_PBS_FCS_3.1_Custom_Add_Well_A1.001.fcs
fcsparser/tests/data/FlowCytometers/MiltenyiBiotec/FCS3.1/EY_2013-07-19_PBS_FCS_3.1_Custom_Without_Add_Well_A1.001.fcs
fcsparser/tests/data/FlowCytometers/MiltenyiBiotec/FCS3.1/EY_2013-07-19_PBS_FCS_3.1_Well_A1.001.fcs
fcsparser/tests/data/FlowCytometers/MiltenyiBiotec/FCS3.1/SG_2014-09-26_Duplicate_Names.fcs
fcsparser/tests/data/FlowCytometers/MiltenyiBiotec/FCS3.1/info.txt
fcsparser/tests/data/FlowCytometers/corrupted/corrupted.fcs
fcsparser/tests/data/FlowCytometers/cyflow_cube_8/cyflow_cube_8.fcs
fcsparser/tests/data/FlowCytometers/cytek-nl-2000/sample_header.fcs
fcsparser/tests/data/FlowCytometers/fake_bitmask_error/fcs1_cleaned.lmd
fcsparser/tests/data/FlowCytometers/fake_large_fcs/fake_large_fcs.fcs
fcsparser/tests/test_fcs_reader.py
fcsparser/version.py
fcsparser-0.2.6.dist-info/LICENSE
fcsparser-0.2.6.dist-info/WHEEL
fcsparser-0.2.6.dist-info/METADATA
fcsparser-0.2.6.dist-info/RECORD
