Metadata-Version: 2.1
Name: fcsparser
Version: 0.2.6
Summary: A python package for reading raw fcs files
Home-page: https://www.github.com/eyurtsev/kor
License: MIT
Keywords: flow cytometry,data analysis,cytometry,parser,data
Author: Eugene Yurtsev
Author-email: eyurtsev@gmail.com
Requires-Python: >=3.8.0,<4.0.0
Classifier: Intended Audience :: Science/Research
Classifier: License :: OSI Approved :: MIT License
Classifier: Programming Language :: Python :: 3
Classifier: Programming Language :: Python :: 3.8
Classifier: Programming Language :: Python :: 3.9
Classifier: Programming Language :: Python :: 3.10
Classifier: Programming Language :: Python :: 3.11
Classifier: Programming Language :: Python :: 3
Classifier: Topic :: Scientific/Engineering :: Bio-Informatics
Classifier: Topic :: Scientific/Engineering :: Medical Science Apps.
Requires-Dist: numpy (>=1,<2)
Requires-Dist: pandas (>=1.5.3,<2.0.0)
Project-URL: Repository, https://www.github.com/eyurtsev/kor
